[
  {
    "type": "post",
    "url": "/v1/user/",
    "title": "create user.",
    "version": "0.1.0",
    "name": "createUser",
    "group": "User",
    "parameter": {
      "fields": {
        "Parameter": [
          {
            "group": "Parameter",
            "type": "<p>String</p> ",
            "optional": false,
            "field": "name",
            "description": "<p>Name of the User.</p> "
          },
          {
            "group": "Parameter",
            "type": "<p>String</p> ",
            "optional": false,
            "field": "lastName",
            "description": "<p>LastName of the User.</p> "
          },
          {
            "group": "Parameter",
            "type": "<p>String</p> ",
            "optional": false,
            "field": "email",
            "description": "<p>email of the User.</p> "
          },
          {
            "group": "Parameter",
            "type": "<p>String</p> ",
            "optional": false,
            "field": "password",
            "description": "<p>of the User.</p> "
          }
        ]
      }
    },
    "success": {
      "fields": {
        "Success 200": [
          {
            "group": "Success 200",
            "type": "<p>Number</p> ",
            "optional": false,
            "field": "code",
            "description": "<p>C贸digo 0 good.</p> "
          },
          {
            "group": "Success 200",
            "type": "<p>Bool</p> ",
            "optional": false,
            "field": "true/false",
            "description": "<p>True o false.</p> "
          }
        ]
      },
      "examples": [
        {
          "title": "Success-Response:",
          "content": "HTTP/1.1 200 OK\n{\n  \"code\": 0,\n  \"response\": true\n}",
          "type": "json"
        }
      ]
    },
    "error": {
      "fields": {
        "Error 4xx": [
          {
            "group": "Error 4xx",
            "optional": false,
            "field": "UserNotFound",
            "description": "<p>The id of the User was not found.</p> "
          }
        ]
      },
      "examples": [
        {
          "title": "Error-Response:",
          "content": "HTTP/1.1 404 Not Found\n{\n  \"error\": \"UserNotFound\"\n}",
          "type": "json"
        }
      ]
    },
    "filename": "api/v1/route.js",
    "groupTitle": "User"
  },
  {
    "type": "delete",
    "url": "/v1/user/",
    "title": "delete user.",
    "version": "0.1.0",
    "name": "deleteUser",
    "group": "User",
    "parameter": {
      "fields": {
        "Parameter": [
          {
            "group": "Parameter",
            "type": "<p>String</p> ",
            "optional": false,
            "field": "id",
            "description": "<p>id of the User.</p> "
          }
        ]
      }
    },
    "success": {
      "fields": {
        "Success 200": [
          {
            "group": "Success 200",
            "type": "<p>Number</p> ",
            "optional": false,
            "field": "code",
            "description": "<p>C贸digo 0 good.</p> "
          },
          {
            "group": "Success 200",
            "type": "<p>Bool</p> ",
            "optional": false,
            "field": "true/false",
            "description": "<p>True o false.</p> "
          }
        ]
      },
      "examples": [
        {
          "title": "Success-Response:",
          "content": "HTTP/1.1 200 OK\n{\n  \"code\": 0,\n  \"response\": true\n}",
          "type": "json"
        }
      ]
    },
    "error": {
      "fields": {
        "Error 4xx": [
          {
            "group": "Error 4xx",
            "optional": false,
            "field": "UserNotFound",
            "description": "<p>The id of the User was not found.</p> "
          }
        ]
      },
      "examples": [
        {
          "title": "Error-Response:",
          "content": "HTTP/1.1 404 Not Found\n{\n  \"error\": \"UserNotFound\"\n}",
          "type": "json"
        }
      ]
    },
    "filename": "api/v1/route.js",
    "groupTitle": "User"
  },
  {
    "type": "get",
    "url": "/v1/user/",
    "title": "get all users.",
    "version": "0.1.0",
    "name": "getUser",
    "group": "User",
    "success": {
      "fields": {
        "Success 200": [
          {
            "group": "Success 200",
            "type": "<p>Number</p> ",
            "optional": false,
            "field": "code",
            "description": "<p>C贸digo 0 good.</p> "
          },
          {
            "group": "Success 200",
            "type": "<p>Bool</p> ",
            "optional": false,
            "field": "true/false",
            "description": "<p>True o false.</p> "
          }
        ]
      },
      "examples": [
        {
          "title": "Success-Response:",
          "content": "HTTP/1.1 200 OK\n{\n  \"code\": 0,\n  \"response\": true\n}",
          "type": "json"
        }
      ]
    },
    "error": {
      "fields": {
        "Error 4xx": [
          {
            "group": "Error 4xx",
            "optional": false,
            "field": "UserNotFound",
            "description": "<p>The id of the User was not found.</p> "
          }
        ]
      },
      "examples": [
        {
          "title": "Error-Response:",
          "content": "HTTP/1.1 404 Not Found\n{\n  \"error\": \"UserNotFound\"\n}",
          "type": "json"
        }
      ]
    },
    "filename": "api/v1/route.js",
    "groupTitle": "User"
  },
  {
    "type": "put",
    "url": "/v1/user/",
    "title": "update user.",
    "version": "0.1.0",
    "name": "updateUser",
    "group": "User",
    "parameter": {
      "fields": {
        "Parameter": [
          {
            "group": "Parameter",
            "type": "<p>String</p> ",
            "optional": false,
            "field": "id",
            "description": "<p>id of the User.</p> "
          },
          {
            "group": "Parameter",
            "type": "<p>String</p> ",
            "optional": false,
            "field": "name",
            "description": "<p>Name of the User.</p> "
          },
          {
            "group": "Parameter",
            "type": "<p>String</p> ",
            "optional": false,
            "field": "lastName",
            "description": "<p>LastName of the User.</p> "
          },
          {
            "group": "Parameter",
            "type": "<p>String</p> ",
            "optional": false,
            "field": "email",
            "description": "<p>email of the User.</p> "
          },
          {
            "group": "Parameter",
            "type": "<p>String</p> ",
            "optional": false,
            "field": "password",
            "description": "<p>of the User.</p> "
          }
        ]
      }
    },
    "success": {
      "fields": {
        "Success 200": [
          {
            "group": "Success 200",
            "type": "<p>Number</p> ",
            "optional": false,
            "field": "code",
            "description": "<p>C贸digo 0 good.</p> "
          },
          {
            "group": "Success 200",
            "type": "<p>Bool</p> ",
            "optional": false,
            "field": "true/false",
            "description": "<p>True o false.</p> "
          }
        ]
      },
      "examples": [
        {
          "title": "Success-Response:",
          "content": "HTTP/1.1 200 OK\n{\n  \"code\": 0,\n  \"response\": true\n}",
          "type": "json"
        }
      ]
    },
    "error": {
      "fields": {
        "Error 4xx": [
          {
            "group": "Error 4xx",
            "optional": false,
            "field": "UserNotFound",
            "description": "<p>The id of the User was not found.</p> "
          }
        ]
      },
      "examples": [
        {
          "title": "Error-Response:",
          "content": "HTTP/1.1 404 Not Found\n{\n  \"error\": \"UserNotFound\"\n}",
          "type": "json"
        }
      ]
    },
    "filename": "api/v1/route.js",
    "groupTitle": "User"
  }
]